google/__init__.py
google/cloud/__init__.py
google/cloud/sqlcommenter/__init__.py
google/cloud/sqlcommenter/flask.py
google/cloud/sqlcommenter/opencensus.py
google/cloud/sqlcommenter/opentelemetry.py
google/cloud/sqlcommenter/django/__init__.py
google/cloud/sqlcommenter/django/middleware.py
google/cloud/sqlcommenter/psycopg2/__init__.py
google/cloud/sqlcommenter/psycopg2/extension.py
google/cloud/sqlcommenter/sqlalchemy/__init__.py
google/cloud/sqlcommenter/sqlalchemy/executor.py
google_cloud_sqlcommenter-2.0.0.dist-info/METADATA
google_cloud_sqlcommenter-2.0.0.dist-info/WHEEL
google_cloud_sqlcommenter-2.0.0.dist-info/top_level.txt
google_cloud_sqlcommenter-2.0.0.dist-info/RECORD
