Metadata-Version: 2.1
Name: google-cloud-sqlcommenter
Version: 2.0.0
Summary: Augment SQL statements with meta information about frameworks and the running environment.
Home-page: UNKNOWN
Author: Google Developers
Author-email: sqlcommenter@googlegroups.com
License: BSD
Platform: UNKNOWN
Classifier: Development Status :: 4 - Beta
Classifier: Environment :: Web Environment
Classifier: Intended Audience :: Developers
Classifier: License :: OSI Approved :: BSD License
Classifier: Operating System :: OS Independent
Classifier: Programming Language :: Python :: 3
Classifier: Programming Language :: Python :: 3.6
Classifier: Programming Language :: Python :: 3.7
Classifier: Programming Language :: Python :: 3.8
Classifier: Programming Language :: Python :: 3.9
Classifier: Topic :: Utilities
Classifier: Framework :: Django
Classifier: Framework :: Django :: 2.1
Classifier: Framework :: Django :: 2.2
Provides-Extra: django
Provides-Extra: flask
Provides-Extra: psycopg2
Provides-Extra: sqlalchemy
Provides-Extra: opencensus
Provides-Extra: opentelemetry
